fw_gear_rtp2_preproc/__init__.py
fw_gear_rtp2_preproc/main.py
fw_gear_rtp2_preproc/parser.py
fw_gear_rtp2_preproc/preprocs.py
fw_gear_rtp2_preproc/utils.py
fw_gear_rtp2_preproc-0.2.4.dist-info/LICENSE
fw_gear_rtp2_preproc-0.2.4.dist-info/METADATA
fw_gear_rtp2_preproc-0.2.4.dist-info/WHEEL
fw_gear_rtp2_preproc-0.2.4.dist-info/RECORD
